guided_capture/__init__.py
guided_capture/core.py
guided_capture-0.1.0.dist-info/licenses/LICENSE
guided_capture-0.1.0.dist-info/METADATA
guided_capture-0.1.0.dist-info/WHEEL
guided_capture-0.1.0.dist-info/top_level.txt
guided_capture-0.1.0.dist-info/RECORD
