Metadata-Version: 2.4
Name: guided-capture
Version: 0.1.0
Summary: An AI-powered library for conducting structured interviews
Home-page: https://github.com/yourusername/guided-capture
Author: Your Name
Author-email: Your Name <your.email@example.com>
License: MIT
Requires-Python: >=3.7
License-File: LICENSE
Requires-Dist: openai>=1.0.0
Provides-Extra: dev
Requires-Dist: pytest>=7.0.0; extra == "dev"
Requires-Dist: black>=22.0.0; extra == "dev"
Requires-Dist: isort>=5.0.0; extra == "dev"
Requires-Dist: mypy>=0.900; extra == "dev"
Dynamic: author
Dynamic: home-page
Dynamic: license-file
Dynamic: requires-python
